{
  "doctor_profile": {
    "doctor_id": "199190",
    "profile_url": "https://nobat.ir/l6wb",
    "nice_id": "l6wb",
    "name": "دکتر پروانه ساکت",
    "specialty": "متخصص پوست و مو (درماتولوژی)",
    "medical_code": "متخصصشماره نظام: ۲۷۲۴۱",
    "verified": false,
    "followers_count": null,
    "reviews_count": 109,
    "rating_percent": 96.0,
    "rating_score_5": 4.8,
    "biography": null,
    "social_media": {},
    "phones": [
      "۰۲۱-۸۸۰۵****",
      "۰۲۱-۸۸۰۵****"
    ],
    "offices": [
      {
        "office_id": "179436",
        "title": "آدرس و تلفن مطب دکتر پروانه ساکت",
        "address": "تهران ملاصدرا - بین خیابان شیخ بهایی و شیراز - پلاک ۱۰۹ - طبقه اول زمان نوبت شما تقریبی وساعت حضور شما در مطب میباشد زمان انتظار در مطب حدود ۱ الی ۲ ساعت میباشد لطفا صبور باشید",
        "description": "شنبه و یکشنبه و دوشنبه عصر‌ها سه شنبه و چهارشنبه صبح‌ها",
        "phones": [
          "۰۲۱-۸۸۰۵****"
        ],
        "holiday_note": ""
      }
    ],
    "schedule": []
  },
  "comments": [
    {
      "text": "جوش صورت",
      "rate": 5.0,
      "label": 1,
      "date": "۱۴۰۴/۰۹/۱۱",
      "like": 0,
      "dislike": 0
    },
    {
      "text": "ریزش مو",
      "rate": 2.5,
      "label": 0,
      "date": "۱۴۰۴/۰۱/۲۰",
      "like": 0,
      "dislike": 0
    },
    {
      "text": "حساسیت دست به مواد ژلیش ناخن",
      "rate": 5.0,
      "label": 1,
      "date": "۱۴۰۳/۱۱/۱۳",
      "like": 0,
      "dislike": 0
    },
    {
      "text": "عالی بودن",
      "rate": 5.0,
      "label": 1,
      "date": "۱۴۰۴/۰۳/۱۰",
      "like": 0,
      "dislike": 0
    },
    {
      "text": "خیلی خوبن",
      "rate": 5.0,
      "label": 1,
      "date": "۱۴۰۰/۱۱/۲۱",
      "like": 0,
      "dislike": 0
    },
    {
      "text": "آلرژی و کهیر پوستی داشتم که با داروی ایشون خیلی زود برطرف شد",
      "rate": 5.0,
      "label": 1,
      "date": "۱۴۰۴/۰۷/۲۲",
      "like": 0,
      "dislike": 0
    },
    {
      "text": "در حال درمان هستم",
      "rate": 5.0,
      "label": 1,
      "date": "۱۴۰۴/۰۸/۱۷",
      "like": 0,
      "dislike": 0
    },
    {
      "text": "ریزش مو فعلا هیچی",
      "rate": 2.5,
      "label": 0,
      "date": "۱۴۰۳/۰۷/۱۸",
      "like": 0,
      "dislike": 0
    },
    {
      "text": "اکنه پسرم با یک نسخه درمان شدن.",
      "rate": 5.0,
      "label": 1,
      "date": "۱۴۰۴/۰۳/۰۴",
      "like": 0,
      "dislike": 0
    },
    {
      "text": "جوش ولک صورت داشتم نتیجهای خوبی گ فتم",
      "rate": 5.0,
      "label": 1,
      "date": "۱۳۹۸/۰۲/۲۶",
      "like": 0,
      "dislike": 0
    },
    {
      "text": "لک وجوش وعالی بود",
      "rate": 5.0,
      "label": 1,
      "date": "۱۳۹۹/۱۲/۰۴",
      "like": 0,
      "dislike": 0
    },
    {
      "text": "از نظر من بهترین دکتر پوست",
      "rate": 5.0,
      "label": 1,
      "date": "۱۴۰۰/۱۰/۱۴",
      "like": 0,
      "dislike": 0
    },
    {
      "text": "خوب است",
      "rate": 5.0,
      "label": 1,
      "date": "۱۴۰۱/۰۷/۲۸",
      "like": 0,
      "dislike": 0
    },
    {
      "text": "دکتر محرب هستند",
      "rate": 5.0,
      "label": 1,
      "date": "۱۴۰۳/۰۶/۱۵",
      "like": 0,
      "dislike": 0
    },
    {
      "text": "خانم دکتر بسیار خوش برخورد و بادانشی هستند و از نتیجه معالجشون خیلی راضیم.",
      "rate": 5.0,
      "label": 1,
      "date": "۱۴۰۴/۰۶/۰۳",
      "like": 0,
      "dislike": 0
    },
    {
      "text": "تشخیص و درمانشون",
      "rate": 5.0,
      "label": 1,
      "date": "۱۳۹۹/۰۷/۰۸",
      "like": 0,
      "dislike": 0
    },
    {
      "text": "تحتدر مانم",
      "rate": 5.0,
      "label": 1,
      "date": "۱۴۰۳/۱۱/۱۵",
      "like": 0,
      "dislike": 0
    },
    {
      "text": "برای مشکلات ریزش موبه ایشون مراجعه کردم تازمان مصرف داروهاخوب بود",
      "rate": 5.0,
      "label": 1,
      "date": "۱۴۰۳/۱۱/۰۹",
      "like": 0,
      "dislike": 0
    },
    {
      "text": "عالی عالی عالی",
      "rate": 5.0,
      "label": 1,
      "date": "۱۳۹۷/۱۰/۰۵",
      "like": 0,
      "dislike": 0
    },
    {
      "text": "دکتر بسیار مجرب و حاذقی هستند",
      "rate": 5.0,
      "label": 1,
      "date": "۱۴۰۱/۰۹/۲۵",
      "like": 0,
      "dislike": 0
    },
    {
      "text": "خانم دکتر بسیار خوش برخورد و ماهر",
      "rate": 5.0,
      "label": 1,
      "date": "۱۴۰۴/۰۵/۰۷",
      "like": 0,
      "dislike": 0
    },
    {
      "text": "فعلا تحت درمانم",
      "rate": 2.5,
      "label": 0,
      "date": "۱۴۰۴/۰۸/۰۵",
      "like": 0,
      "dislike": 0
    },
    {
      "text": "راضی بودم",
      "rate": 5.0,
      "label": 1,
      "date": "۱۳۹۹/۱۲/۱۸",
      "like": 0,
      "dislike": 0
    },
    {
      "text": "ایشان بینظیر هستند",
      "rate": 5.0,
      "label": 1,
      "date": "۱۳۹۹/۰۹/۲۸",
      "like": 0,
      "dislike": 0
    },
    {
      "text": "من مشکل پسوریازیس دارم .در کل دکتر خوبی هستن",
      "rate": 5.0,
      "label": 1,
      "date": "۱۴۰۳/۰۵/۰۶",
      "like": 0,
      "dislike": 0
    },
    {
      "text": "درمان سفیدی زودرس مو",
      "rate": 5.0,
      "label": 1,
      "date": "۱۴۰۱/۰۱/۱۳",
      "like": 0,
      "dislike": 0
    },
    {
      "text": "ریزش مو",
      "rate": 5.0,
      "label": 1,
      "date": "۱۴۰۲/۰۶/۲۹",
      "like": 0,
      "dislike": 0
    },
    {
      "text": "ریزش مو",
      "rate": 5.0,
      "label": 1,
      "date": "۱۴۰۲/۰۶/۰۶",
      "like": 0,
      "dislike": 0
    },
    {
      "text": "مشکل من حاد نبود ولی در کل راضی بودم",
      "rate": 5.0,
      "label": 1,
      "date": "۱۴۰۱/۰۹/۱۴",
      "like": 0,
      "dislike": 0
    },
    {
      "text": "دکتر خوب و با",
      "rate": 5.0,
      "label": 1,
      "date": "۱۴۰۴/۰۷/۰۵",
      "like": 0,
      "dislike": 0
    },
    {
      "text": "مشکل اگزماکه با یک نسخه درمان شد",
      "rate": 5.0,
      "label": 1,
      "date": "۱۴۰۳/۰۷/۲۱",
      "like": 0,
      "dislike": 0
    },
    {
      "text": "ایشون عالی هستن",
      "rate": 5.0,
      "label": 1,
      "date": "۱۴۰۳/۰۲/۱۱",
      "like": 0,
      "dislike": 0
    },
    {
      "text": "سلام پسرم ریزش مو داشتن فعلا یک جلسه جواب دادن",
      "rate": 5.0,
      "label": 1,
      "date": "۱۴۰۴/۰۶/۱۱",
      "like": 0,
      "dislike": 0
    },
    {
      "text": "برای درمان آکنه مراجعه کرده بودم که نتیجه خیلی بهتری نسبت به سایر پزشکان حاصل شد",
      "rate": 5.0,
      "label": 1,
      "date": "۱۴۰۳/۰۸/۰۶",
      "like": 0,
      "dislike": 0
    },
    {
      "text": "عالی بودن",
      "rate": 5.0,
      "label": 1,
      "date": "۱۳۹۹/۰۱/۲۲",
      "like": 0,
      "dislike": 0
    },
    {
      "text": "عالی،تشخیص و درمان",
      "rate": 5.0,
      "label": 1,
      "date": "۱۴۰۰/۱۰/۱۸",
      "like": 0,
      "dislike": 0
    },
    {
      "text": "عالی نامبروان",
      "rate": 5.0,
      "label": 1,
      "date": "۱۴۰۳/۰۷/۰۶",
      "like": 0,
      "dislike": 0
    },
    {
      "text": "خوب بود",
      "rate": 2.5,
      "label": 0,
      "date": "۱۴۰۲/۱۱/۲۷",
      "like": 0,
      "dislike": 0
    },
    {
      "text": "بهداشت و نگهداری پوست",
      "rate": 5.0,
      "label": 1,
      "date": "۱۳۹۹/۱۲/۰۲",
      "like": 0,
      "dislike": 0
    },
    {
      "text": "تشخیص عالی درمان با یک نسخه",
      "rate": 5.0,
      "label": 1,
      "date": "۱۴۰۳/۰۸/۰۲",
      "like": 0,
      "dislike": 0
    },
    {
      "text": "عالی بود",
      "rate": 5.0,
      "label": 1,
      "date": "۱۳۹۸/۰۱/۲۲",
      "like": 0,
      "dislike": 0
    },
    {
      "text": "صورتم بود و خوب شدم",
      "rate": 5.0,
      "label": 1,
      "date": "۱۴۰۰/۱۱/۱۱",
      "like": 0,
      "dislike": 0
    },
    {
      "text": "خیلی خوب و عالی",
      "rate": 5.0,
      "label": 1,
      "date": "۱۴۰۴/۰۴/۲۲",
      "like": 0,
      "dislike": 0
    },
    {
      "text": "عالی با خیال",
      "rate": 5.0,
      "label": 1,
      "date": "۱۴۰۲/۱۱/۲۱",
      "like": 0,
      "dislike": 0
    },
    {
      "text": "خوب هستند",
      "rate": 5.0,
      "label": 1,
      "date": "۱۴۰۳/۰۷/۰۲",
      "like": 0,
      "dislike": 0
    },
    {
      "text": "رفتار خوبی دارند و کاملا به حرف بیمار گوش میدن و متناسب اون نسخه میدن.جوش های صورت من کاملا برطرف شد",
      "rate": 5.0,
      "label": 1,
      "date": "۱۴۰۰/۰۶/۳۰",
      "like": 0,
      "dislike": 0
    },
    {
      "text": "آکنه و نتیجه خوبی گرفتم.",
      "rate": 5.0,
      "label": 1,
      "date": "۱۴۰۳/۰۸/۲۱",
      "like": 0,
      "dislike": 0
    },
    {
      "text": "دکتر بسیار کار درست",
      "rate": 5.0,
      "label": 1,
      "date": "۱۴۰۴/۰۹/۲۵",
      "like": 0,
      "dislike": 0
    },
    {
      "text": "عالی بودن",
      "rate": 5.0,
      "label": 1,
      "date": "۱۴۰۰/۰۶/۱۸",
      "like": 0,
      "dislike": 0
    },
    {
      "text": "سلام، من برای مشکل پوستی مراجعه کردم و رضایت داشتم، الان برای ریزش مو، میخواهم پیش ایشان برم",
      "rate": 5.0,
      "label": 1,
      "date": "۱۴۰۱/۰۳/۱۰",
      "like": 0,
      "dislike": 0
    },
    {
      "text": "در حال درمان",
      "rate": 5.0,
      "label": 1,
      "date": "۱۴۰۳/۰۴/۰۲",
      "like": 0,
      "dislike": 0
    },
    {
      "text": "بهترین هستند باتجربه برخورد خیلی خوب دارند وقت زیاد برای مریض میزارن .وهمچنین از لحاظ درمان مریض خیلی سریع ب جواب عالی میرسی.من برای درمان خود ایمنی پوستی مراجعه کردم در حال درمان هستم .از همان اول درمان شروع ب بهبودی کردم",
      "rate": 5.0,
      "label": 1,
      "date": "۱۴۰۴/۱۱/۲۸",
      "like": 0,
      "dislike": 0
    },
    {
      "text": "جوش صورت",
      "rate": 5.0,
      "label": 1,
      "date": "۱۴۰۲/۱۲/۱۷",
      "like": 0,
      "dislike": 0
    },
    {
      "text": "بهترین",
      "rate": 5.0,
      "label": 1,
      "date": "۱۴۰۰/۰۷/۲۷",
      "like": 0,
      "dislike": 0
    },
    {
      "text": "درمان جوش",
      "rate": 5.0,
      "label": 1,
      "date": "۱۴۰۰/۱۲/۱۲",
      "like": 0,
      "dislike": 0
    },
    {
      "text": "کار زیبایی",
      "rate": 5.0,
      "label": 1,
      "date": "۱۴۰۲/۱۰/۰۵",
      "like": 0,
      "dislike": 0
    },
    {
      "text": "سال هاست که پزشکم ایشان هستن و بسیار راضی هستم",
      "rate": 5.0,
      "label": 1,
      "date": "۱۴۰۴/۰۱/۱۱",
      "like": 0,
      "dislike": 0
    },
    {
      "text": "جوش صورت فعلا در حال معالجه هستم",
      "rate": 5.0,
      "label": 1,
      "date": "۱۴۰۳/۰۷/۲۷",
      "like": 0,
      "dislike": 0
    },
    {
      "text": "بنده و خانواده ام ب دلایل مختلف پیش ایشون مراجعه کردیم و همیشه خداروشکر نتیجه مطلوب گرفتیم",
      "rate": 5.0,
      "label": 1,
      "date": "۱۴۰۳/۰۸/۱۴",
      "like": 0,
      "dislike": 0
    },
    {
      "text": "مشکل پوستی",
      "rate": 5.0,
      "label": 1,
      "date": "۱۴۰۴/۰۳/۰۲",
      "like": 0,
      "dislike": 0
    },
    {
      "text": "دکتر صبور و بسیار کار بلد",
      "rate": 5.0,
      "label": 1,
      "date": "۱۴۰۴/۰۹/۱۰",
      "like": 0,
      "dislike": 0
    },
    {
      "text": "عالی بودند",
      "rate": 5.0,
      "label": 1,
      "date": "۱۴۰۰/۰۴/۳۰",
      "like": 0,
      "dislike": 0
    },
    {
      "text": "روزنه باز پوست عالی بود\nبا1 جلسه کلی تغییر کردم",
      "rate": 5.0,
      "label": 1,
      "date": "۱۳۹۷/۱۲/۰۳",
      "like": 0,
      "dislike": 0
    },
    {
      "text": "جوش ولک",
      "rate": 5.0,
      "label": 1,
      "date": "۱۴۰۱/۰۲/۲۲",
      "like": 0,
      "dislike": 0
    },
    {
      "text": "خوب بود",
      "rate": 5.0,
      "label": 1,
      "date": "۱۳۹۹/۱۲/۰۳",
      "like": 0,
      "dislike": 0
    },
    {
      "text": "من ریزش شدید مو داشتم",
      "rate": 5.0,
      "label": 1,
      "date": "۱۴۰۳/۰۳/۲۱",
      "like": 0,
      "dislike": 0
    },
    {
      "text": "هایپرکراتوز داشتم و با کمک ایشان برطرف شد",
      "rate": 5.0,
      "label": 1,
      "date": "۱۴۰۰/۱۰/۲۰",
      "like": 0,
      "dislike": 0
    },
    {
      "text": "سلام خیلب خوب هستن",
      "rate": 5.0,
      "label": 1,
      "date": "۱۳۹۸/۰۱/۲۰",
      "like": 0,
      "dislike": 0
    },
    {
      "text": "مشکل پوست",
      "rate": 5.0,
      "label": 1,
      "date": "۱۴۰۰/۰۶/۳۱",
      "like": 0,
      "dislike": 0
    },
    {
      "text": "بسیار با حوصله و دقیق هستند",
      "rate": 5.0,
      "label": 1,
      "date": "۱۴۰۱/۰۹/۲۲",
      "like": 0,
      "dislike": 0
    },
    {
      "text": "بسیار عالی",
      "rate": 5.0,
      "label": 1,
      "date": "۱۴۰۲/۰۷/۰۷",
      "like": 0,
      "dislike": 0
    },
    {
      "text": "لیزر ککو",
      "rate": 5.0,
      "label": 1,
      "date": "۱۴۰۴/۰۳/۰۷",
      "like": 0,
      "dislike": 0
    },
    {
      "text": "پزشکیکه بادقت زیاد مفاینه وتشخیص درست میدهند.من درمانم هنوز ادامه دارد.بنابر این نمیتوانم امتیاز بدهم",
      "rate": 2.5,
      "label": 0,
      "date": "۱۴۰۴/۰۹/۲۲",
      "like": 0,
      "dislike": 0
    },
    {
      "text": "خوب هست",
      "rate": 5.0,
      "label": 1,
      "date": "۱۳۹۸/۰۹/۲۴",
      "like": 0,
      "dislike": 0
    },
    {
      "text": "به نظرم بهترین پزشک در زمینه پوست و مشکلات پوستی هستند . به همه پیشنهاد میکنم",
      "rate": 5.0,
      "label": 1,
      "date": "۱۴۰۴/۰۷/۰۳",
      "like": 0,
      "dislike": 0
    },
    {
      "text": "بسیار خوب",
      "rate": 5.0,
      "label": 1,
      "date": "۱۴۰۱/۰۱/۰۳",
      "like": 0,
      "dislike": 0
    },
    {
      "text": "در مورد جوش صورت مراجعه کردم خوب بودن",
      "rate": 5.0,
      "label": 1,
      "date": "۱۴۰۳/۰۵/۲۷",
      "like": 0,
      "dislike": 0
    }
  ]
}